[
  {
    "id": "corner-the-market",
    "name": "Corner the Market",
    "condition": "Control 4 planets that each have the same planet trait.",
    "isSecret": false,
    "points": 1,
    "source": "base"
  },
  {
    "id": "develop-weaponry",
    "name": "Develop Weaponry",
    "condition": "Own 2 unit upgrade technologies.",
    "isSecret": false,
    "points": 1,
    "source": "base"
  },
  {
    "id": "diversify-research",
    "name": "Diversify Research",
    "condition": "Own 2 technologies in each of 2 colors.",
    "isSecret": false,
    "points": 1,
    "source": "base"
  },
  {
    "id": "erect-a-monument",
    "name": "Erect a Monument",
    "condition": "Spend 8 resources.",
    "isSecret": false,
    "points": 1,
    "source": "base"
  },
  {
    "id": "expand-borders",
    "name": "Expand Borders",
    "condition": "Control 6 planets in non-home systems.",
    "isSecret": false,
    "points": 1,
    "source": "base"
  },
  {
    "id": "found-research-outposts",
    "name": "Found Research Outposts",
    "condition": "Control 3 planets that have technology specialties.",
    "isSecret": false,
    "points": 1,
    "source": "base"
  },
  {
    "id": "intimidate-council",
    "name": "Intimidate Council",
    "condition": "Have 1 or more ships in 2 systems that are adjacent to Mecatol Rex's System.",
    "isSecret": false,
    "points": 1,
    "source": "base"
  },
  {
    "id": "lead-from-the-front",
    "name": "Lead from the Front",
    "condition": "Spend a total of 3 tokens from your tactic and/or strategy pools.",
    "isSecret": false,
    "points": 1,
    "source": "base"
  },
  {
    "id": "negotiate-trade-routes",
    "name": "Negotiate Trade Routes",
    "condition": "Spend 5 trade goods.",
    "isSecret": false,
    "points": 1,
    "source": "base"
  },
  {
    "id": "sway-the-council",
    "name": "Sway the Council",
    "condition": "Spend 8 influence.",
    "isSecret": false,
    "points": 1,
    "source": "base"
  },
  {
    "id": "amass-wealth",
    "name": "Amass Wealth",
    "condition": "Spend 3 influence, 3 resources, and 3 trade goods.",
    "isSecret": false,
    "points": 1,
    "source": "pok"
  },
  {
    "id": "build-defenses",
    "name": "Build Defenses",
    "condition": "Have 4 or more structures.",
    "isSecret": false,
    "points": 1,
    "source": "pok"
  },
  {
    "id": "discover-lost-outposts",
    "name": "Discover Lost Outposts",
    "condition": "Control 2 planets that have attachments.",
    "isSecret": false,
    "points": 1,
    "source": "pok"
  },
  {
    "id": "engineer-a-marvel",
    "name": "Engineer a Marvel",
    "condition": "Have your flagship or a war sun on the game board.",
    "isSecret": false,
    "points": 1,
    "source": "pok"
  },
  {
    "id": "explore-deep-space",
    "name": "Explore Deep Space",
    "condition": "Have units in 3 systems that do not contain planets.",
    "isSecret": false,
    "points": 1,
    "source": "pok"
  },
  {
    "id": "improve-infrastructure",
    "name": "Improve Infrastructure",
    "condition": "Have structures on 3 planets outside of your home system.",
    "isSecret": false,
    "points": 1,
    "source": "pok"
  },
  {
    "id": "make-history",
    "name": "Make History",
    "condition": "Have units in 2 systems that contain legendary planets, Mecatol Rex, or anomalies.",
    "isSecret": false,
    "points": 1,
    "source": "pok"
  },
  {
    "id": "populate-the-outer-rim",
    "name": "Populate the Outer Rim",
    "condition": "Have units in 3 systems on the edge of the game board other than your home system.",
    "isSecret": false,
    "points": 1,
    "source": "pok"
  },
  {
    "id": "push-boundaries",
    "name": "Push Boundaries",
    "condition": "Control more planets than each of 2 of your neighbors.",
    "isSecret": false,
    "points": 1,
    "source": "pok"
  },
  {
    "id": "raise-a-fleet",
    "name": "Raise a Fleet",
    "condition": "Have 5 or more non-fighter ships in 1 system.",
    "isSecret": false,
    "points": 1,
    "source": "pok"
  },
  {
    "id": "centralize-galactic-trade",
    "name": "Centralize Galactic Trade",
    "condition": "Spend 10 trade goods.",
    "isSecret": false,
    "points": 2,
    "source": "base"
  },
  {
    "id": "conquer-the-weak",
    "name": "Conquer the Weak",
    "condition": "Control 1 planet that is in another player's home system.",
    "isSecret": false,
    "points": 2,
    "source": "base"
  },
  {
    "id": "form-galactic-brain-trust",
    "name": "Form Galactic Brain Trust",
    "condition": "Control 5 planets that have technology specialties.",
    "isSecret": false,
    "points": 2,
    "source": "base"
  },
  {
    "id": "found-a-golden-age",
    "name": "Found a Golden Age",
    "condition": "Spend 16 resources.",
    "isSecret": false,
    "points": 2,
    "source": "base"
  },
  {
    "id": "galvanize-the-people",
    "name": "Galvanize the People",
    "condition": "Spend a total of 6 tokens from your tactic and/or strategy pools.",
    "isSecret": false,
    "points": 2,
    "source": "base"
  },
  {
    "id": "manipulate-galactic-law",
    "name": "Manipulate Galactic Law",
    "condition": "Spend 16 influence.",
    "isSecret": false,
    "points": 2,
    "source": "base"
  },
  {
    "id": "master-the-sciences",
    "name": "Master the Sciences",
    "condition": "Own 2 technologies in each of 4 colors.",
    "isSecret": false,
    "points": 2,
    "source": "base"
  },
  {
    "id": "revolutionize-warfare",
    "name": "Revolutionize Warfare",
    "condition": "Own 3 unit upgrade technologies.",
    "isSecret": false,
    "points": 2,
    "source": "base"
  },
  {
    "id": "subdue-the-galaxy",
    "name": "Subdue the Galaxy",
    "condition": "Control 11 planets in non-home systems.",
    "isSecret": false,
    "points": 2,
    "source": "base"
  },
  {
    "id": "unify-the-colonies",
    "name": "Unify the Colonies",
    "condition": "Control 6 planets that each have the same planet trait.",
    "isSecret": false,
    "points": 2,
    "source": "base"
  },
  {
    "id": "achieve-supremacy",
    "name": "Achieve Supremacy",
    "condition": "Have your flagship or a war sun in another player's home system or the Mecatol Rex system.",
    "isSecret": false,
    "points": 2,
    "source": "pok"
  },
  {
    "id": "become-a-legend",
    "name": "Become a Legend",
    "condition": "Have units in 4 systems that contain legendary planets, Mecatol Rex, or anomalies.",
    "isSecret": false,
    "points": 2,
    "source": "pok"
  },
  {
    "id": "command-an-armada",
    "name": "Command an Armada",
    "condition": "Have 8 or more non-fighter ships in 1 system.",
    "isSecret": false,
    "points": 2,
    "source": "pok"
  },
  {
    "id": "construct-massive-cities",
    "name": "Construct Massive Cities",
    "condition": "Have 7 or more structures.",
    "isSecret": false,
    "points": 2,
    "source": "pok"
  },
  {
    "id": "control-the-borderlands",
    "name": "Control the Borderlands",
    "condition": "Have units in 5 systems on the edge of the game board other than your home system.",
    "isSecret": false,
    "points": 2,
    "source": "pok"
  },
  {
    "id": "hold-vast-reserves",
    "name": "Hold Vast Reserves",
    "condition": "Spend 6 influence, 6 resources, and 6 trade goods.",
    "isSecret": false,
    "points": 2,
    "source": "pok"
  },
  {
    "id": "patrol-vast-territories",
    "name": "Patrol Vast Territories",
    "condition": "Have units in 5 systems that do not contain planets.",
    "isSecret": false,
    "points": 2,
    "source": "pok"
  },
  {
    "id": "protect-the-border",
    "name": "Protect the Border",
    "condition": "Have structures on 5 planets outside of your home system.",
    "isSecret": false,
    "points": 2,
    "source": "pok"
  },
  {
    "id": "reclaim-ancient-monuments",
    "name": "Reclaim Ancient Monuments",
    "condition": "Control 3 planets that have attachments.",
    "isSecret": false,
    "points": 2,
    "source": "pok"
  },
  {
    "id": "rule-distant-lands",
    "name": "Rule Distant Lands",
    "condition": "Control 2 planets that are each in or adjacent to a different, other player's home system.",
    "isSecret": false,
    "points": 2,
    "source": "pok"
  },
  {
    "id": "destroy-their-greatest-ship",
    "name": "Destroy Their Greatest Ship",
    "condition": "Destroy another player's war sun or flagship.",
    "isSecret": true,
    "points": 1,
    "source": "base"
  },
  {
    "id": "make-an-example-of-their-world",
    "name": "Make an Example of Their World",
    "condition": "Use BOMBARDMENT to destroy the last of a player's ground forces on a planet.",
    "isSecret": true,
    "points": 1,
    "source": "base"
  },
  {
    "id": "spark-a-rebellion",
    "name": "Spark a Rebellion",
    "condition": "Win a combat against a player who has the most victory points.",
    "isSecret": true,
    "points": 1,
    "source": "base"
  },
  {
    "id": "turn-their-fleets-to-dust",
    "name": "Turn Their Fleets to Dust",
    "condition": "Use SPACE CANNON to destroy the last of a player's ships in a system.",
    "isSecret": true,
    "points": 1,
    "source": "base"
  },
  {
    "id": "unveil-flagship",
    "name": "Unveil Flagship",
    "condition": "Win a space combat in a system that contains your flagship. You cannot score this objective if your flagship is destroyed in the combat.",
    "isSecret": true,
    "points": 1,
    "source": "base"
  },
  {
    "id": "become-a-martyr",
    "name": "Become a Martyr",
    "condition": "Lose control of a planet in a home system.",
    "isSecret": true,
    "points": 1,
    "source": "pok"
  },
  {
    "id": "betray-a-friend",
    "name": "Betray a Friend",
    "condition": "Win a combat against a player whose promissory note you had in your play area at the start of your tactical action.",
    "isSecret": true,
    "points": 1,
    "source": "pok"
  },
  {
    "id": "brave-the-void",
    "name": "Brave the Void",
    "condition": "Win a combat in an anomaly.",
    "isSecret": true,
    "points": 1,
    "source": "pok"
  },
  {
    "id": "darken-the-skies",
    "name": "Darken the Skies",
    "condition": "Win a combat in another player's home system.",
    "isSecret": true,
    "points": 1,
    "source": "pok"
  },
  {
    "id": "demonstrate-your-power",
    "name": "Demonstrate Your Power",
    "condition": "Have 3 or more non-fighter ships in the active system at the end of a space combat.",
    "isSecret": true,
    "points": 1,
    "source": "pok"
  },
  {
    "id": "fight-with-precision",
    "name": "Fight With Precision",
    "condition": "Use ANTI-FIGHTER BARRAGE to destroy the last of a player's fighters in a system.",
    "isSecret": true,
    "points": 1,
    "source": "pok"
  },
  {
    "id": "prove-endurance",
    "name": "Prove Endurance",
    "condition": "Be the last player to pass during a game round.",
    "isSecret": true,
    "points": 1,
    "source": "pok"
  },
  {
    "id": "adapt-new-strategies",
    "name": "Adapt New Strategies",
    "condition": "Own 2 faction technologies. (Valefar Assimilator technologies do not count toward this objective.)",
    "isSecret": true,
    "points": 1,
    "source": "base"
  },
  {
    "id": "become-the-gatekeeper",
    "name": "Become the Gatekeeper",
    "condition": "Have 1 or more ships in a system that contains an alpha wormhole and 1 or more ships in a system that contains a beta wormhole.",
    "isSecret": true,
    "points": 1,
    "source": "base"
  },
  {
    "id": "control-the-region",
    "name": "Control the Region",
    "condition": "Have 1 or more ships in 6 systems.",
    "isSecret": true,
    "points": 1,
    "source": "base"
  },
  {
    "id": "cut-supply-lines",
    "name": "Cut Supply Lines",
    "condition": "Have 1 or more ships in the same system as another player's space dock.",
    "isSecret": true,
    "points": 1,
    "source": "base"
  },
  {
    "id": "establish-a-perimeter",
    "name": "Establish a Perimeter",
    "condition": "Have 4 PDS units on the game board.",
    "isSecret": true,
    "points": 1,
    "source": "base"
  },
  {
    "id": "forge-an-alliance",
    "name": "Forge an Alliance",
    "condition": "Control 4 cultural planets.",
    "isSecret": true,
    "points": 1,
    "source": "base"
  },
  {
    "id": "form-a-spy-network",
    "name": "Form a Spy Network",
    "condition": "Discard 5 Action Cards.",
    "isSecret": true,
    "points": 1,
    "source": "base"
  },
  {
    "id": "fuel-the-war-machine",
    "name": "Fuel the War Machine",
    "condition": "Have 3 space docks on the game board.",
    "isSecret": true,
    "points": 1,
    "source": "base"
  },
  {
    "id": "gather-a-mighty-fleet",
    "name": "Gather a Mighty Fleet",
    "condition": "Have 5 dreadnoughts on the game board.",
    "isSecret": true,
    "points": 1,
    "source": "base"
  },
  {
    "id": "learn-the-secrets-of-the-cosmos",
    "name": "Learn the Secrets of the Cosmos",
    "condition": "Have 1 or more ships in 3 systems that are each adjacent to an anomaly.",
    "isSecret": true,
    "points": 1,
    "source": "base"
  },
  {
    "id": "master-the-laws-of-physics",
    "name": "Master the Laws of Physics",
    "condition": "Own 4 technologies of the same color.",
    "isSecret": true,
    "points": 1,
    "source": "base"
  },
  {
    "id": "mine-rare-metals",
    "name": "Mine Rare Metals",
    "condition": "Control 4 hazardous planets.",
    "isSecret": true,
    "points": 1,
    "source": "base"
  },
  {
    "id": "monopolize-production",
    "name": "Monopolize Production",
    "condition": "Control 4 industrial planets.",
    "isSecret": true,
    "points": 1,
    "source": "base"
  },
  {
    "id": "occupy-the-seat-of-the-empire",
    "name": "Occupy the Seat of the Empire",
    "condition": "Control Mecatol Rex and have 3 or more ships in its system.",
    "isSecret": true,
    "points": 1,
    "source": "base"
  },
  {
    "id": "threaten-enemies",
    "name": "Threaten Enemies",
    "condition": "Have 1 or more ships in a system that is adjacent to another player's home system.",
    "isSecret": true,
    "points": 1,
    "source": "base"
  },
  {
    "id": "defy-space-and-time",
    "name": "Defy Space and Time",
    "condition": "Have units in the wormhole nexus.",
    "isSecret": true,
    "points": 1,
    "source": "pok"
  },
  {
    "id": "destroy-heretical-works",
    "name": "Destroy Heretical Works",
    "condition": "Purge 2 of your relic fragments of any type.",
    "isSecret": true,
    "points": 1,
    "source": "pok"
  },
  {
    "id": "establish-hegemony",
    "name": "Establish Hegemony",
    "condition": "Control planets that have a combined influence value of at least 12.",
    "isSecret": true,
    "points": 1,
    "source": "pok"
  },
  {
    "id": "foster-cohesion",
    "name": "Foster Cohesion",
    "condition": "Be neighbors with all other players.",
    "isSecret": true,
    "points": 1,
    "source": "pok"
  },
  {
    "id": "hoard-raw-materials",
    "name": "Hoard Raw Materials",
    "condition": "Control planets that have a combined resource value of at least 12.",
    "isSecret": true,
    "points": 1,
    "source": "pok"
  },
  {
    "id": "mechanize-the-military",
    "name": "Mechanize The Military",
    "condition": "Have 1 mech on each of 4 planets.",
    "isSecret": true,
    "points": 1,
    "source": "pok"
  },
  {
    "id": "occupy-the-fringe",
    "name": "Occupy The Fringe",
    "condition": "Have 9 or more ground forces on a planet that does not contain 1 of your space docks.",
    "isSecret": true,
    "points": 1,
    "source": "pok"
  },
  {
    "id": "produce-en-masse",
    "name": "Produce En Masse",
    "condition": "Have units with a combined PRODUCTION value of at least 8 in a single system.",
    "isSecret": true,
    "points": 1,
    "source": "pok"
  },
  {
    "id": "seize-an-icon",
    "name": "Seize An Icon",
    "condition": "Control a legendary planet.",
    "isSecret": true,
    "points": 1,
    "source": "pok"
  },
  {
    "id": "stake-your-claim",
    "name": "Stake your Claim",
    "condition": "Control a planet in a system that contains a planet controlled by another player.",
    "isSecret": true,
    "points": 1,
    "source": "pok"
  },
  {
    "id": "strengthen-bonds",
    "name": "Strengthen Bonds",
    "condition": "Have another player's promissory note in your play area.",
    "isSecret": true,
    "points": 1,
    "source": "pok"
  },
  {
    "id": "dictate-policy",
    "name": "Dictate Policy",
    "condition": "There are 3 or more laws in play.",
    "isSecret": true,
    "points": 1,
    "source": "pok"
  },
  {
    "id": "drive-the-debate",
    "name": "Drive the Debate",
    "condition": "You or a planet you control are elected by an agenda.",
    "isSecret": true,
    "points": 1,
    "source": "pok"
  }
]
